jola/__init__.py
jola/config.py
jola/dataloaders.py
jola/dataset.py
jola/evaluate.py
jola/modeling_llama.py
jola/modeling_qwen2.py
jola/trainers.py
jola/trainers_mlp.py
jola-0.0.1.dist-info/LICENSE
jola-0.0.1.dist-info/METADATA
jola-0.0.1.dist-info/WHEEL
jola-0.0.1.dist-info/top_level.txt
jola-0.0.1.dist-info/RECORD
