Metadata-Version: 2.2
Name: jola
Version: 0.0.1
Summary: JoLA: Joint Localization and Activation Editing for Low-Resource Fine-Tuning
Home-page: https://github.com/wenlai-lavine/jola
Author: Wen Lai
Author-email: wen.lai@tum.de
License: Apache License 2.0
Classifier: Development Status :: 3 - Alpha
Classifier: Intended Audience :: Science/Research
Classifier: License :: OSI Approved :: MIT License
Classifier: Operating System :: POSIX :: Linux
Classifier: Programming Language :: Python :: 3
Classifier: Programming Language :: Python :: 3.8
Classifier: Programming Language :: Python :: 3.9
Requires-Python: >=3.8
License-File: LICENSE
Requires-Dist: torch>=2.5.1
Requires-Dist: transformers==4.45.1
Requires-Dist: trl==0.8.1
Requires-Dist: datasets>=3.2.0
Requires-Dist: wandb
Dynamic: author
Dynamic: author-email
Dynamic: classifier
Dynamic: description
Dynamic: description-content-type
Dynamic: home-page
Dynamic: license
Dynamic: requires-dist
Dynamic: requires-python
Dynamic: summary
